phovision/__init__.py
phovision/filters.py
phovision/io.py
phovision-0.1.5.dist-info/licenses/LICENSE
phovision-0.1.5.dist-info/METADATA
phovision-0.1.5.dist-info/WHEEL
phovision-0.1.5.dist-info/top_level.txt
phovision-0.1.5.dist-info/RECORD
